plasmidrender/__init__.py
plasmidrender/main.py
plasmidrender/option.py
plasmidrender/svg_draw.py
plasmidrender-1.1.6.dist-info/LICENSE
plasmidrender-1.1.6.dist-info/METADATA
plasmidrender-1.1.6.dist-info/WHEEL
plasmidrender-1.1.6.dist-info/entry_points.txt
plasmidrender-1.1.6.dist-info/top_level.txt
plasmidrender-1.1.6.dist-info/RECORD
