Metadata-Version: 2.1
Name: plasmidrender
Version: 1.1.6
Summary: CLI tool to illustrate plasmids with a structure described by json.
Home-page: https://github.com/strelka145/Plasmid_render
Author: strelka
Author-email: irohaprg@gmail.com
Classifier: Programming Language :: Python :: 3
Classifier: License :: OSI Approved :: MIT License
Classifier: Operating System :: OS Independent
License-File: LICENSE
Requires-Dist: playwright
